sprite_nvqMinh/__init__.py
sprite_nvqMinh/spriteutil.py
Sprite_sheet_project-1.2.3.dist-info/LICENSE
Sprite_sheet_project-1.2.3.dist-info/METADATA
Sprite_sheet_project-1.2.3.dist-info/WHEEL
Sprite_sheet_project-1.2.3.dist-info/top_level.txt
Sprite_sheet_project-1.2.3.dist-info/RECORD
