Metadata-Version: 2.1
Name: Sprite-sheet-project
Version: 1.2.3
Summary: A useful tool to find sprite image
Home-page: https://github.com/intek-training-jsc/sprite-sheet-nvqMinh29101992.git
Author: Minh Quoc
Author-email: minh.nong@f4.intek.edu.vn
License: UNKNOWN
Platform: UNKNOWN
Classifier: Programming Language :: Python :: 3
Classifier: License :: OSI Approved :: MIT License
Classifier: Operating System :: OS Independent
Requires-Python: >=3.6
Requires-Dist: bleach (==3.1.0)
Requires-Dist: certifi (==2019.11.28)
Requires-Dist: cffi (==1.13.2)
Requires-Dist: chardet (==3.0.4)
Requires-Dist: cryptography (==2.8)
Requires-Dist: docutils (==0.16)
Requires-Dist: idna (==2.8)
Requires-Dist: keyring (==21.1.0)
Requires-Dist: more-itertools (==8.1.0)
Requires-Dist: numpy (==1.18.1)
Requires-Dist: pillow (==7.0.0)
Requires-Dist: pkginfo (==1.5.0.1)
Requires-Dist: pycparser (==2.19)
Requires-Dist: pygments (==2.5.2)
Requires-Dist: readme-renderer (==24.0)
Requires-Dist: requests (==2.22.0)
Requires-Dist: requests-toolbelt (==0.9.1)
Requires-Dist: six (==1.14.0)
Requires-Dist: tqdm (==4.41.1)
Requires-Dist: twine (==3.1.1)
Requires-Dist: urllib3 (==1.25.7)
Requires-Dist: webencodings (==0.5.1)
Requires-Dist: wheel (==0.33.6)
Requires-Dist: zipp (==2.0.0)
Requires-Dist: importlib-metadata (==1.4.0) ; python_version < "3.8"
Requires-Dist: jeepney (==0.4.2) ; sys_platform == "linux"
Requires-Dist: secretstorage (==3.1.2) ; sys_platform == "linux"
